youchat.py
youchat_py-1.2.3.dist-info/LICENSE
youchat_py-1.2.3.dist-info/METADATA
youchat_py-1.2.3.dist-info/WHEEL
youchat_py-1.2.3.dist-info/entry_points.txt
youchat_py-1.2.3.dist-info/top_level.txt
youchat_py-1.2.3.dist-info/RECORD
