Metadata-Version: 2.1
Name: youchat-py
Version: 1.2.3
Summary: Simple communication with YouChat in python.
License: BSD 2-Clause License
Project-URL: Homepage, https://github.com/yaroslav4167/youchat-py
Project-URL: Bug Reports, https://github.com/yaroslav4167/youchat-py/issues
Project-URL: Source, https://github.com/yaroslav4167/youchat-py
Keywords: chatbot,youchat
Classifier: Development Status :: 5 - Production/Stable
Classifier: Intended Audience :: Developers
Classifier: Intended Audience :: Education
Classifier: Intended Audience :: Science/Research
Classifier: Topic :: Software Development :: Libraries :: Python Modules
Classifier: Topic :: Scientific/Engineering :: Artificial Intelligence
Classifier: License :: OSI Approved :: BSD License
Classifier: Programming Language :: Python :: 3
Classifier: Programming Language :: Python :: 3.7
Classifier: Programming Language :: Python :: 3.8
Classifier: Programming Language :: Python :: 3.9
Classifier: Programming Language :: Python :: 3.10
Classifier: Programming Language :: Python :: 3.11
Classifier: Programming Language :: Python :: 3 :: Only
Classifier: Operating System :: OS Independent
Requires-Python: >=3.7
License-File: LICENSE
Requires-Dist: seleniumbase
Provides-Extra: dev
Requires-Dist: check-manifest; extra == "dev"
Provides-Extra: test
Requires-Dist: coverage; extra == "test"
